galspec/COcoeff
galspec/K17_Table7
galspec/__init__.py
galspec/coeffBonato
galspec/coeff_Rangwala
galspec/coeff_spinoglio
galspec/spectrumCreate.py
galspec-0.2.6.dist-info/LICENSE
galspec-0.2.6.dist-info/METADATA
galspec-0.2.6.dist-info/WHEEL
galspec-0.2.6.dist-info/top_level.txt
galspec-0.2.6.dist-info/RECORD
