Metadata-Version: 2.1
Name: galspec
Version: 0.2.6
Summary: Creates sample galaxy spectra in the GHz/THz range
Home-page: https://github.com/deshima-dev/GalSpec
Author: Tom Bakx (edits: Stefanie Brackenhoff)
License: UNKNOWN
Platform: UNKNOWN
Classifier: Programming Language :: Python :: 3
Classifier: License :: OSI Approved :: MIT License
Classifier: Operating System :: OS Independent
Requires-Python: >=3.6
